ziptimezone/__init__.py
ziptimezone/addon.py
ziptimezone/batch_processor.py
ziptimezone/core.py
ziptimezone/data_manager.py
ziptimezone/geocode.py
ziptimezone/globals.py
ziptimezone/mappings.py
ziptimezone-1.1.8.dist-info/LICENSE
ziptimezone-1.1.8.dist-info/METADATA
ziptimezone-1.1.8.dist-info/WHEEL
ziptimezone-1.1.8.dist-info/RECORD
