Metadata-Version: 2.1
Name: ziptimezone
Version: 1.1.8
Summary: A package to convert ZIP codes to time zones and get geographic coordinates.
License: MIT
Author: Manjunath Bettadapura
Author-email: manjunathbettadapura412@gmail.com
Requires-Python: >=3.9,<4.0
Classifier: License :: OSI Approved :: MIT License
Classifier: Programming Language :: Python :: 3
Classifier: Programming Language :: Python :: 3.9
Classifier: Programming Language :: Python :: 3.10
Classifier: Programming Language :: Python :: 3.11
Classifier: Programming Language :: Python :: 3.12
Requires-Dist: astral (>=3.2,<4.0)
Requires-Dist: python-dateutil (>=2.8,<3.0)
Requires-Dist: pytz (>=2024.1,<2025.0)
Requires-Dist: requests (>=2.31.0,<3.0.0)
Requires-Dist: timezonefinder (>=6.1.5,<=6.5.0)
